hf_model_inspector/__init__.py
hf_model_inspector/analyzer.py
hf_model_inspector/formatter.py
hf_model_inspector/hf_model_inspector.py
hf_model_inspector/loader.py
hf_model_inspector/utils.py
hf_model_inspector-1.2.2.dist-info/METADATA
hf_model_inspector-1.2.2.dist-info/WHEEL
hf_model_inspector-1.2.2.dist-info/licenses/LICENSE
hf_model_inspector-1.2.2.dist-info/RECORD
