Metadata-Version: 2.4
Name: hf-model-inspector
Version: 1.2.2
Summary: A package and GitHub Action to generate quality reports on Hugging Face model stats and usage, addressing ambiguity in open model releases.
Project-URL: homepage, https://github.com/ParagEkbote/hf-model-inspector
Project-URL: repository, https://github.com/ParagEkbote/hf-model-inspector
Project-URL: issues, https://github.com/ParagEkbote/hf-model-inspector/issues
Author-email: Parag Ekbote <paragekbote23@gmail.com>
License: Apache-2.0
License-File: LICENSE
Classifier: Development Status :: 4 - Beta
Classifier: Intended Audience :: Developers
Classifier: License :: OSI Approved :: Apache Software License
Classifier: Programming Language :: Python :: 3.10
Classifier: Topic :: Software Development :: Libraries :: Python Modules
Requires-Python: >=3.9
Requires-Dist: huggingface-hub>=0.24.0
Requires-Dist: python-dotenv>=1.0.0
Requires-Dist: transformers>=4.21.0
